s3iotools/__init__.py
s3iotools/__init__.pyc
s3iotools/_version.py
s3iotools/_version.pyc
s3iotools/cli.py
s3iotools/compat.py
s3iotools/compat.pyc
s3iotools/config.py
s3iotools/config.pyc
s3iotools/docs/__init__.py
s3iotools/io/__init__.py
s3iotools/io/__init__.pyc
s3iotools/io/dataframe.py
s3iotools/io/dataframe.pyc
s3iotools/io/file_object.py
s3iotools/io/file_object.pyc
s3iotools/tests/__init__.py
s3iotools/tests/__init__.pyc
s3iotools/tests/customers.tsv
s3iotools/tests/fake_s3_obj.py
s3iotools/tests/fake_s3_obj.pyc
s3iotools/tests/io_dataframe.py
s3iotools/tests/io_dataframe.pyc
s3iotools/tests/moto_compat.py
s3iotools/tests/moto_compat.pyc
s3iotools/utils/__init__.py
s3iotools/utils/__init__.pyc
s3iotools/utils/fingerprint.py
s3iotools/utils/pandas_mate.py
s3iotools/utils/s3_obj_filter.py
s3iotools/utils/s3_obj_filter.pyc
s3iotools/utils/s3_url_builder.py
s3iotools/utils/s3_url_builder.pyc
s3iotools/utils/tester.py
s3iotools-0.0.3.dist-info/AUTHORS.rst
s3iotools-0.0.3.dist-info/LICENSE.txt
s3iotools-0.0.3.dist-info/METADATA
s3iotools-0.0.3.dist-info/WHEEL
s3iotools-0.0.3.dist-info/top_level.txt
s3iotools-0.0.3.dist-info/RECORD
