Metadata-Version: 2.1
Name: s3iotools
Version: 0.0.3
Summary: Make S3 file object read/write easier, support raw file, csv, parquet, pandas.DataFrame.
Home-page: https://github.com/MacHu-GWU/
Author: Sanhe Hu
Author-email: husanhe@gmail.com
Maintainer: Unknown
License: MIT
Download-URL: https://pypi.python.org/pypi/s3iotools/0.0.3#downloads
Platform: Windows
Platform: MacOS
Platform: Unix
Classifier: Development Status :: 4 - Beta
Classifier: Intended Audience :: Developers
Classifier: License :: OSI Approved :: MIT License
Classifier: Natural Language :: English
Classifier: Operating System :: Microsoft :: Windows
Classifier: Operating System :: MacOS
Classifier: Operating System :: Unix
Classifier: Programming Language :: Python
Classifier: Programming Language :: Python :: 2.7
Classifier: Programming Language :: Python :: 3.4
Classifier: Programming Language :: Python :: 3.5
Classifier: Programming Language :: Python :: 3.6
Requires-Dist: attrs
Requires-Dist: attrs-mate
Requires-Dist: pathlib-mate
Requires-Dist: boto3
Provides-Extra: docs
Requires-Dist: sphinx (==1.8.1) ; extra == 'docs'
Requires-Dist: sphinx-rtd-theme ; extra == 'docs'
Requires-Dist: sphinx-jinja ; extra == 'docs'
Requires-Dist: sphinx-copybutton ; extra == 'docs'
Requires-Dist: docfly (>=0.0.17) ; extra == 'docs'
Requires-Dist: rstobj (>=0.0.5) ; extra == 'docs'
Requires-Dist: pygments ; extra == 'docs'
Provides-Extra: tests
Requires-Dist: pytest (==3.2.3) ; extra == 'tests'
Requires-Dist: pytest-cov (==2.5.1) ; extra == 'tests'
Requires-Dist: boto (==2.36.0) ; extra == 'tests'
Requires-Dist: boto3 (==1.9.86) ; extra == 'tests'
Requires-Dist: moto ; extra == 'tests'
Requires-Dist: pandas ; extra == 'tests'
Requires-Dist: pyarrow ; extra == 'tests'
